{
  "_class": "symbolInstance",
  "do_objectID": "6AEA54C3-87B3-41B9-A10B-E2CD1F8D5979",
  "exportOptions": {
    "_class": "exportOptions",
    "exportFormats": [
    ],
    "includedLayerIds": [
    ],
    "layerOptions": 0,
    "shouldTrim": false
  },
  "frame": {
    "_class": "rect",
    "constrainProportions": false,
    "height": 42,
    "width": 290,
    "x": 516,
    "y": 122
  },
  "horizontalSpacing": 0,
  "isFlippedHorizontal": false,
  "isFlippedVertical": false,
  "isLocked": false,
  "isVisible": true,
  "layerListExpandedType": 0,
  "masterInfluenceEdgeMaxXPadding": 1,
  "masterInfluenceEdgeMaxYPadding": 1,
  "masterInfluenceEdgeMinXPadding": 1,
  "masterInfluenceEdgeMinYPadding": 1,
  "name": "login_facebook",
  "nameIsFixed": false,
  "resizingConstraint": 63,
  "resizingType": 0,
  "rotation": 0,
  "shouldBreakMaskChain": false,
  "style": {
    "_class": "style",
    "endDecorationType": 0,
    "miterLimit": 10,
    "startDecorationType": 0
  },
  "symbolID": "4B0E65A9-CC4E-41E8-89B0-86B87C865481",
  "verticalSpacing": 0
}